espresso/__init__.py
espressopy-0.0.1.dist-info/LICENSE
espressopy-0.0.1.dist-info/METADATA
espressopy-0.0.1.dist-info/WHEEL
espressopy-0.0.1.dist-info/top_level.txt
espressopy-0.0.1.dist-info/RECORD
