Metadata-Version: 2.1
Name: espressopy
Version: 0.0.1
Summary: The new way to create Discord bots.
License-File: LICENSE
Requires-Dist: websockets
Requires-Dist: asyncio
